heatpro/__init__.py
heatpro/check/__init__.py
heatpro/check/check_data_format.py
heatpro/check/check_weight_format.py
heatpro/demand_profile/__init__.py
heatpro/demand_profile/building_heating_profile.py
heatpro/demand_profile/hot_water_profile.py
heatpro/demand_profile/loss_profile.py
heatpro/disaggregation/__init__.py
heatpro/disaggregation/pipeline.py
heatpro/disaggregation/weighted_disaggregation.py
heatpro/district_heating_load.py
heatpro/external_factors/__init__.py
heatpro/external_factors/external_factors.py
heatpro/external_factors/process/__init__.py
heatpro/external_factors/process/closed_heating_season.py
heatpro/external_factors/process/heating_season.py
heatpro/external_factors/process/temperature_cold_water.py
heatpro/external_factors/process/temperature_departure.py
heatpro/external_factors/process/temperature_return.py
heatpro/external_factors/process/temperature_soil.py
heatpro/external_factors/process/utils.py
heatpro/special_hot_water.py
heatpro/temporal_demand/__init__.py
heatpro/temporal_demand/daily_heat_demand.py
heatpro/temporal_demand/hourly_heat_demand.py
heatpro/temporal_demand/monthly_heat_demand.py
heatpro/temporal_demand/temporal_heat_demand.py
heatpro/temporal_demand/yearly_heat_demand.py
heatpro-0.1.5.dist-info/AUTHORS.rst
heatpro-0.1.5.dist-info/LICENSE.txt
heatpro-0.1.5.dist-info/METADATA
heatpro-0.1.5.dist-info/WHEEL
heatpro-0.1.5.dist-info/RECORD
