Metadata-Version: 2.1
Name: heatpro
Version: 0.1.5
Summary: Generate heat demand load profile for distict heating
License: CECILL-B
Author: Robinson Beaucour
Author-email: robinson.beaucour@cea.fr
Requires-Python: >=3.9,<4.0
Classifier: License :: CeCILL-B Free Software License Agreement (CECILL-B)
Classifier: Programming Language :: Python :: 3
Classifier: Programming Language :: Python :: 3.9
Classifier: Programming Language :: Python :: 3.10
Classifier: Programming Language :: Python :: 3.11
Classifier: Programming Language :: Python :: 3.12
Requires-Dist: matplotlib (>=3.8.4,<4.0.0)
Requires-Dist: pandas (>=2.1.0,<3.0.0)
